<com.cloudbees.jenkins.plugins.sshcredentials.impl.BasicSSHUserPrivateKey plugin="ssh-credentials@1.13">
  <scope>SYSTEM</scope>
  <id>id-jenkins-slave</id>
  <description>jenkins-slave</description>
  <username>jenkins-slave</username>
  <privateKeySource class="com.cloudbees.jenkins.plugins.sshcredentials.impl.BasicSSHUserPrivateKey$DirectEntryPrivateKeySource">
    <privateKey>
      <secret-redacted/>
    </privateKey>
  </privateKeySource>
</com.cloudbees.jenkins.plugins.sshcredentials.impl.BasicSSHUserPrivateKey>